examon_beginners_package/__init__.py
examon_beginners_package/beginners.py
examon_beginners_package-0.3.1.dist-info/METADATA
examon_beginners_package-0.3.1.dist-info/WHEEL
examon_beginners_package-0.3.1.dist-info/RECORD
