Metadata-Version: 2.1
Name: examon-beginners-package
Version: 0.3.1
Summary: 
Author: Jarrod Folino
Author-email: jdfolino@icloud.com
Requires-Python: >3.9,<3.12
Classifier: Programming Language :: Python :: 3
Classifier: Programming Language :: Python :: 3.10
Classifier: Programming Language :: Python :: 3.11
Requires-Dist: examon-core (==1.4.1)
Requires-Dist: simple-term-menu (>=1.6.1,<2.0.0)
